__init__.py
pupil_metrics.py
pupil_metrics-0.0.1.dist-info/LICENSE
pupil_metrics-0.0.1.dist-info/METADATA
pupil_metrics-0.0.1.dist-info/WHEEL
pupil_metrics-0.0.1.dist-info/top_level.txt
pupil_metrics-0.0.1.dist-info/RECORD
