Metadata-Version: 2.1
Name: pupil-metrics
Version: 0.0.1
Summary: A small package for computing pupil-size metrics over a time-series.
Home-page: https://github.com/wdas03/pupil-metrics
Author: Will Das
Author-email: Will Das <williamhdas@gmail.com>
License: BSD 2-clause
Project-URL: Homepage, https://github.com/wdas03/pupil-metrics
Project-URL: Bug Tracker, https://github.com/wdas03/pupil-metrics/issues
Platform: UNKNOWN
Classifier: Programming Language :: Python :: 3
Classifier: License :: OSI Approved :: BSD License
Classifier: Operating System :: OS Independent
Requires-Python: >=3.7
License-File: LICENSE
Requires-Dist: pandas
Requires-Dist: numpy
